cmplot.py
cmplot-1.0.1.dist-info/LICENSE
cmplot-1.0.1.dist-info/METADATA
cmplot-1.0.1.dist-info/WHEEL
cmplot-1.0.1.dist-info/top_level.txt
cmplot-1.0.1.dist-info/RECORD
