Metadata-Version: 2.1
Name: cmplot
Version: 1.0.1
Summary: Cloudy Mountain Plot
Home-page: https://github.com/g-insana/cmplot.py
Author: Dr Giuseppe Insana
Author-email: insana@insana.net
License: AGPL
Platform: UNKNOWN
Classifier: Programming Language :: Python :: 3
Classifier: License :: OSI Approved :: GNU Affero General Public License v3
Classifier: Operating System :: OS Independent
Requires-Python: >=3.5
Requires-Dist: plotly
Requires-Dist: numpy
Requires-Dist: pandas
Requires-Dist: scipy
